README.md
setup.py
ad_geo_backend/__init__.py
ad_geo_backend/model.py
ad_geo_backend/shell.py
ad_geo_backend.egg-info/PKG-INFO
ad_geo_backend.egg-info/SOURCES.txt
ad_geo_backend.egg-info/dependency_links.txt
ad_geo_backend.egg-info/entry_points.txt
ad_geo_backend.egg-info/requires.txt
ad_geo_backend.egg-info/top_level.txt
ad_geo_backend/backends/__init__.py
ad_geo_backend/backends/abstract.py
ad_geo_backend/backends/geonames_db.py
ad_geo_backend/backends/mongodb.py
ad_geo_backend/utils/__init__.py
ad_geo_backend/utils/bing.py
ad_geo_backend/utils/cmd_line_utils.py
ad_geo_backend/utils/common.py
ad_geo_backend/utils/file_utils.py
ad_geo_backend/utils/google.py