Metadata-Version: 1.0
Name: ad-geo-backend
Version: 1.2.2
Summary: Geographical data management
Home-page: https://github.com/dolead/ad-geo-backend
Author: Dolead
Author-email: backend@dolead.com
License: UNKNOWN
Platform: UNKNOWN
